MANIFEST.in
README.md
README.rst
setup.cfg
setup.py
toolsbk/__init__.py
toolsbk/toolsbk.py
toolsbk.egg-info/PKG-INFO
toolsbk.egg-info/SOURCES.txt
toolsbk.egg-info/dependency_links.txt
toolsbk.egg-info/entry_points.txt
toolsbk.egg-info/top_level.txt