Metadata-Version: 1.0
Name: toolsbk
Version: 0.1
Summary: Backup your usefull tools
Home-page: https://gitorious.org/tools-backup/
Author: Antoine Durand
Author-email: antoinedurand.ad@gmail.com
License: UNKNOWN
Platform: UNKNOWN
